nr_nresults/__init__.py
nr_nresults/config.py
nr_nresults/constants.py
nr_nresults/ext.py
nr_nresults/fetchers.py
nr_nresults/jsonschemas/__init__.py
nr_nresults/jsonschemas/nr_nresults/__init__.py
nr_nresults/jsonschemas/nr_nresults/nr-nresults-v1.0.0.json
nr_nresults/mapping_includes/__init__.py
nr_nresults/mapping_includes/v7/__init__.py
nr_nresults/mapping_includes/v7/nr-taxonomies-Nresults-v1.0.0.json
nr_nresults/mappings/__init__.py
nr_nresults/mappings/v7/__init__.py
nr_nresults/mappings/v7/nr_nresults/__init__.py
nr_nresults/mappings/v7/nr_nresults/nr-nresults-v1.0.0.json
nr_nresults/marshmallow/__init__.py
nr_nresults/marshmallow/json.py
nr_nresults/marshmallow/subschemas.py
nr_nresults/minters.py
nr_nresults/providers.py
nr_nresults/record.py
nr_nresults/search.py
techlib_nr_nresults-1.0.0a20.dist-info/entry_points.txt
techlib_nr_nresults-1.0.0a20.dist-info/LICENSE
techlib_nr_nresults-1.0.0a20.dist-info/WHEEL
techlib_nr_nresults-1.0.0a20.dist-info/METADATA
techlib_nr_nresults-1.0.0a20.dist-info/RECORD
