Metadata-Version: 2.1
Name: techlib-nr-nresults
Version: 1.0.0a20
Summary: National repository Nresults metadata model
License: MIT
Keywords: National repository,events
Author: Daniel Kopecký
Author-email: Daniel.Kopecky@techlib.cz
Requires-Python: >=3.8,<4.0
Classifier: Development Status :: 3 - Alpha
Classifier: Environment :: Web Environment
Classifier: Intended Audience :: Developers
Classifier: License :: OSI Approved :: MIT License
Classifier: Operating System :: OS Independent
Classifier: Programming Language :: Python
Classifier: Programming Language :: Python :: 3
Classifier: Programming Language :: Python :: 3.8
Classifier: Programming Language :: Python :: 3.9
Classifier: Topic :: Internet :: WWW/HTTP :: Dynamic Content
Classifier: Topic :: Software Development :: Libraries :: Python Modules
Requires-Dist: techlib-nr-common (>=3.0.0a45,<4.0.0)
